piver/__init__.py
piver/options.py
piver/piver.py
piver/store.py
piver/exception/__init__.py
piver/exception/config.py
piver/exception/file.py
piver/util/__init__.py
piver/util/do_parser.py
piver/util/env.py
piver/util/file.py
piver/util/file_type.py
piver-0.0.1.dist-info/LICENSE
piver-0.0.1.dist-info/METADATA
piver-0.0.1.dist-info/WHEEL
piver-0.0.1.dist-info/top_level.txt
piver-0.0.1.dist-info/RECORD
