Metadata-Version: 2.1
Name: piver
Version: 0.0.1
Summary: A Python library for reading and managing configuration files.
Home-page: https://github.com/lfcypo/piver
Author: lfcypo
Author-email: lfcypo@gmail.com
License: MIT
Classifier: Programming Language :: Python :: 3
Classifier: License :: OSI Approved :: MIT License
Classifier: Operating System :: OS Independent
License-File: LICENSE
Requires-Dist: toml
